augment/__init__.py
augment/agent.py
augment/exceptions.py
augment/function_tools.py
augment/listener.py
augment/listener_adapter.py
augment/prompt_formatter.py
augment/acp/__init__.py
augment/acp/claude_code_client.py
augment/acp/client.py
augment/acp/test_client_e2e.py
augment_sdk-0.1.1.dist-info/licenses/LICENSE
augment_sdk-0.1.1.dist-info/METADATA
augment_sdk-0.1.1.dist-info/WHEEL
augment_sdk-0.1.1.dist-info/entry_points.txt
augment_sdk-0.1.1.dist-info/top_level.txt
augment_sdk-0.1.1.dist-info/RECORD
