Metadata-Version: 2.4
Name: augment-sdk
Version: 0.1.1
Summary: Python SDK for building AI-powered coding workflows with the Augment CLI agent
Author-email: Augment Code <support@augmentcode.com>
License: MIT
Project-URL: Homepage, https://augmentcode.com
Project-URL: Repository, https://github.com/augmentcode/augment-sdk-python
Project-URL: Documentation, https://docs.augmentcode.com
Project-URL: Bug Tracker, https://github.com/augmentcode/augment-sdk-python/issues
Project-URL: Source Code, https://github.com/augmentcode/augment-sdk-python
Keywords: augment,ai,coding,agent,sdk,automation,llm,code-generation
Classifier: Development Status :: 3 - Alpha
Classifier: Intended Audience :: Developers
Classifier: License :: OSI Approved :: MIT License
Classifier: Programming Language :: Python :: 3
Classifier: Programming Language :: Python :: 3.8
Classifier: Programming Language :: Python :: 3.9
Classifier: Programming Language :: Python :: 3.10
Classifier: Programming Language :: Python :: 3.11
Classifier: Programming Language :: Python :: 3.12
Requires-Python: >=3.8
License-File: LICENSE
Requires-Dist: agent-client-protocol>=0.4.5
Provides-Extra: test
Requires-Dist: pytest>=7.0.0; extra == "test"
Requires-Dist: pytest-timeout>=2.1.0; extra == "test"
Provides-Extra: dev
Requires-Dist: pytest>=7.0.0; extra == "dev"
Requires-Dist: pytest-cov>=4.0.0; extra == "dev"
Requires-Dist: black>=22.0.0; extra == "dev"
Requires-Dist: isort>=5.0.0; extra == "dev"
Requires-Dist: mypy>=1.0.0; extra == "dev"
Dynamic: license-file
